resampy2/__init__.py
resampy2/core.py
resampy2/filters.py
resampy2/version.py
resampy2-0.1.1.dist-info/METADATA
resampy2-0.1.1.dist-info/WHEEL
resampy2-0.1.1.dist-info/top_level.txt
resampy2-0.1.1.dist-info/RECORD
