Metadata-Version: 2.1
Name: resampy2
Version: 0.1.1
Summary: Modified resampy package
Home-page: https://github.com/Efshal/boilerplate-monorepo
Author: Efshal Ahmed
Author-email: efshalahmad@gmail.com
License: UNKNOWN
Platform: UNKNOWN
Classifier: Development Status :: 1 - Planning
Classifier: Intended Audience :: Science/Research
Classifier: License :: OSI Approved :: BSD License
Classifier: Operating System :: POSIX :: Linux
Classifier: Programming Language :: Python :: 2
Classifier: Programming Language :: Python :: 2.7
Classifier: Programming Language :: Python :: 3
Classifier: Programming Language :: Python :: 3.4
Classifier: Programming Language :: Python :: 3.5
Requires-Dist: numpy (>=1.17)
Requires-Dist: numba (>=0.53)
